[{
	"title": "After Dark in Central Park",
	"year": 1901
}, {
	"title": "Boarding School Girls' Pajama Parade",
	"year": 1902
}, {
	"title": "Buffalo Bill's Wild West Parad",
	"year": 1903
}, {
	"title": "Caught",
	"year": 1904
}, {
	"title": "Clowns Spinning Hats",
	"year": 1905
}, {
	"title": "Capture of Boer Battery by British",
	"year": 1906
}, {
	"title": "The Enchanted Drawing",
	"year": 1907
}, {
	"title": "Feeding Sea Lions",
	"year": 1908
}, {
	"title": "How to Make a Fat Wife Out of Two Lean Ones",
	"year": 1909
}, {
	"title": "New Life Rescue",
	"year": 1910
}]
